invenio_files_processor/__init__.py
invenio_files_processor/config.py
invenio_files_processor/errors.py
invenio_files_processor/ext.py
invenio_files_processor/proxies.py
invenio_files_processor/signals.py
invenio_files_processor/version.py
invenio_files_processor/processors/__init__.py
invenio_files_processor/processors/processor.py
invenio_files_processor/processors/tika/__init__.py
invenio_files_processor/processors/tika/unpack.py
invenio_files_processor-0.1.0.dist-info/AUTHORS.rst
invenio_files_processor-0.1.0.dist-info/LICENSE
invenio_files_processor-0.1.0.dist-info/METADATA
invenio_files_processor-0.1.0.dist-info/WHEEL
invenio_files_processor-0.1.0.dist-info/entry_points.txt
invenio_files_processor-0.1.0.dist-info/top_level.txt
invenio_files_processor-0.1.0.dist-info/RECORD
